LICENSE
MANIFEST.in
Pipfile
Pipfile.lock
README.md
setup.py
src/botsh/__init__.py
src/botsh/docker_exec.py
src/botsh/history.py
src/botsh/llm.py
src/botsh/logging.py
src/botsh/main.py
src/botsh/prompt.py
src/botsh/task_driver.py
src/botsh.egg-info/PKG-INFO
src/botsh.egg-info/SOURCES.txt
src/botsh.egg-info/dependency_links.txt
src/botsh.egg-info/entry_points.txt
src/botsh.egg-info/requires.txt
src/botsh.egg-info/top_level.txt
src/botsh/templates/prompt.jinja2