Metadata-Version: 2.1
Name: botsh
Version: 0.1.7
Summary: A task runner powered by OpenAI and Docker.
Home-page: https://github.com/drifting-in-space/botsh
Author: Paul Butler
Author-email: paul@driftingin.space
Classifier: Intended Audience :: Developers
Classifier: License :: OSI Approved :: MIT License
Classifier: Programming Language :: Python :: 3
Classifier: Programming Language :: Python :: 3.6
Classifier: Programming Language :: Python :: 3.7
Classifier: Programming Language :: Python :: 3.8
Classifier: Programming Language :: Python :: 3.9
Requires-Python: >=3.6
Provides-Extra: dev
License-File: LICENSE
